ezs3/__init__.py
ezs3-0.2.1.dist-info/LICENSE
ezs3-0.2.1.dist-info/METADATA
ezs3-0.2.1.dist-info/WHEEL
ezs3-0.2.1.dist-info/top_level.txt
ezs3-0.2.1.dist-info/RECORD
