Metadata-Version: 2.1
Name: ezs3
Version: 0.2.1
Summary: S3 wrapper built on top of boto3.
Home-page: https://github.com/nchz/ezs3
Author: nchz
License: UNKNOWN
Platform: UNKNOWN
Requires-Python: >=3.7
License-File: LICENSE
Requires-Dist: boto3 (==1.*)
Requires-Dist: dictdot (==1.*)
